services/__init__.py
services/admin.py
services/apps.py
services/models.py
services/tests.py
services/urls.py
services/views.py
services/migrations/0001_initial.py
services/migrations/__init__.py
cheap_local_websites_services-0.0.1.dist-info/LICENSE
cheap_local_websites_services-0.0.1.dist-info/METADATA
cheap_local_websites_services-0.0.1.dist-info/WHEEL
cheap_local_websites_services-0.0.1.dist-info/top_level.txt
cheap_local_websites_services-0.0.1.dist-info/RECORD
